{
    "created_time": "2025-05-28T00:14:53Z",
    "files": [
        {
            "attachment_folder": "",
            "created_time": "2025-05-28T00:14:53Z",
            "id": "42",
            "modified_time": "2025-05-28T00:14:53Z",
            "name": "_index.md",
            "signature": "16237855340156573053",
            "tags": [
            ]
        }
    ],
    "folders": [
        {
            "name": "bi-awgn-initialize"
        },
        {
            "name": "equalization"
        },
        {
            "name": "polyphase-matched-filtering"
        },
        {
            "name": "timing-recovery"
        }
    ],
    "id": "39",
    "modified_time": "2025-05-28T00:14:53Z",
    "signature": "17276897264378729853",
    "version": 3
}
